maleo/crypto/__init__.py
maleo/crypto/secret.py
maleo/crypto/signature.py
maleo/crypto/token.py
maleo/crypto/encryption/__init__.py
maleo/crypto/encryption/aes.py
maleo/crypto/encryption/rsa.py
maleo/crypto/hash/__init__.py
maleo/crypto/hash/bcrypt.py
maleo/crypto/hash/enums.py
maleo/crypto/hash/hmac.py
maleo/crypto/hash/sha256.py
maleo/crypto/key/__init__.py
maleo/crypto/key/enums.py
maleo/crypto/key/rsa/__init__.py
maleo/crypto/key/rsa/enums.py
maleo/crypto/key/rsa/generator.py
maleo/crypto/key/rsa/loader.py
maleo_crypto-0.0.46.dist-info/licenses/LICENSE
maleo_crypto-0.0.46.dist-info/METADATA
maleo_crypto-0.0.46.dist-info/WHEEL
maleo_crypto-0.0.46.dist-info/top_level.txt
maleo_crypto-0.0.46.dist-info/RECORD
